{
  "success": true,
  "message": "Success",
  "result": "Here's an analysis of the provided scientific image:\n\n**1. Type of Plot/Figure:**\n\nThe figure is a flowchart or schematic diagram. It's not a traditional plot showing data points and their relationships on axes.  Instead, it illustrates the steps and data flow of a computational process.\n\n**2. Main Finding or Conclusion:**\n\nThe figure doesn't present a finding or conclusion in the traditional sense. It describes the architecture and workflow of a method for image manipulation or generation using a combination of Stable Diffusion, LoRA (Low-Rank Adaptation), and ControlNet.  The method appears to use a reference image and text prompt to guide the noise prediction and image generation process. The overall goal is presumably to produce a higher-quality image, possibly based on a degraded input.\n\n**3. Key Data Points or Significant Numbers:**\n\nThere are no quantitative data points or significant numbers presented in this diagram. The figure focuses on the *process* rather than numerical results.  The notations (xref, e, eg,  c<sub>tex</sub>) represent variables (reference image, Gaussian noise, predicted noise, text prompt) within the computational framework.\n\n\n**4. Trend or Relationship:**\n\nThe diagram illustrates the flow of information and computation. The key relationships shown are:\n\n* **Degraded image → ControlNet → Stable Diffusion:** The degraded input image is processed by ControlNet, which in turn feeds information to the Stable Diffusion model.\n* **Reference Image + Gaussian Noise → Stable Diffusion:** A reference image and added Gaussian noise serves as input to the process.\n* **Text Prompt (c<sub>tex</sub>) → Stable Diffusion:** A text prompt (\"A photo of [V]\") guides the image generation process.\n* **LoRA's role:** LoRA is integrated into the Stable Diffusion process, suggesting fine-tuning or adaptation for better performance.\n* **L<sub>tune</sub>:** A loss function (L<sub>tune</sub>) is used to potentially optimize the generation process.\n* **Operation and Gradient Flow:**  The arrows indicate the direction of data flow (black) and gradient updates (light blue) in the system.  This shows how parameter updates are done using the gradient flow, optimizing the generation process.\n\n\nIn summary, the image depicts a computational pipeline for image manipulation using  Stable Diffusion and ancillary models, not presenting any specific numerical results but illustrating the algorithmic workflow and information flow.\n",
  "image_path": "images/8e4850d376d6107f8871eaaf6d81c035f0e91ed42a90a7270630eaa49346e443.jpg",
  "api": "google",
  "reason": null,
  "timestamp": "2025-07-19T18:41:36.419251"
}