{
  "success": true,
  "message": "Alias 'testcmd2' created successfully",
  "alias_name": "testcmd2",
  "alias_command": "echo world",
  "files_processed": 3,
  "files_updated": 3,
  "results": [
    {
      "file": "/Users/wukunhuan/.bash_profile",
      "success": true,
      "created_file": false,
      "updated_existing": false
    },
    {
      "file": "/Users/wukunhuan/.bashrc",
      "success": true,
      "created_file": false,
      "updated_existing": false
    },
    {
      "file": "/Users/wukunhuan/.zshrc",
      "success": true,
      "created_file": false,
      "updated_existing": false
    }
  ]
}